rxntools/__init__.py
rxntools/base.py
rxntools/reaction.py
rxntools/smiles.py
rxntools/substructure.py
rxntools/template.py
rxntools-0.0.2.dist-info/LICENSE
rxntools-0.0.2.dist-info/METADATA
rxntools-0.0.2.dist-info/WHEEL
rxntools-0.0.2.dist-info/top_level.txt
rxntools-0.0.2.dist-info/RECORD
