Metadata-Version: 2.1
Name: rxntools
Version: 0.0.2
Summary: Chemical reaction cheminformatics tools
Home-page: https://github.com/xiangyan93/rxntools
Author: Yan Xiang
Author-email: 1993.xiangyan@gmail.com
License: UNKNOWN
Platform: UNKNOWN
Classifier: Programming Language :: Python
Classifier: License :: OSI Approved :: MIT License
Classifier: Operating System :: OS Independent
Requires-Python: >=3.6
Requires-Dist: numpy (>=1.17)
Requires-Dist: treelib (>=1.6.1)
